dls_pairstream_lib/__init__.py
dls_pairstream_lib/__main__.py
dls_pairstream_lib/_version.py
dls_pairstream_lib/pairstream.py
dls_pairstream_lib/version.py
dls_pairstream_lib/dummy/__init__.py
dls_pairstream_lib/dummy/reader.py
dls_pairstream_lib/dummy/writer.py
dls_pairstream_lib/file/__init__.py
dls_pairstream_lib/file/writer.py
dls_pairstream_lib/websockets/__init__.py
dls_pairstream_lib/websockets/reader.py
dls_pairstream_lib/websockets/writer.py
dls_pairstream_lib/zmq_pubsub/__init__.py
dls_pairstream_lib/zmq_pubsub/reader.py
dls_pairstream_lib/zmq_pubsub/writer.py
dls_pairstream_lib/zmq_pullpush/__init__.py
dls_pairstream_lib/zmq_pullpush/reader.py
dls_pairstream_lib/zmq_pullpush/writer.py
dls_pairstream_lib/zmq_pushpull/__init__.py
dls_pairstream_lib/zmq_pushpull/reader.py
dls_pairstream_lib/zmq_pushpull/writer.py
dls_pairstream-5.0.0.dist-info/LICENSE
dls_pairstream-5.0.0.dist-info/METADATA
dls_pairstream-5.0.0.dist-info/WHEEL
dls_pairstream-5.0.0.dist-info/entry_points.txt
dls_pairstream-5.0.0.dist-info/top_level.txt
dls_pairstream-5.0.0.dist-info/RECORD
